chromedriver_autoinstaller/__init__.py
chromedriver_autoinstaller/utils.py
chromedriver_autoinstaller-0.6.3.dist-info/LICENSE
chromedriver_autoinstaller-0.6.3.dist-info/METADATA
chromedriver_autoinstaller-0.6.3.dist-info/WHEEL
chromedriver_autoinstaller-0.6.3.dist-info/entry_points.txt
chromedriver_autoinstaller-0.6.3.dist-info/top_level.txt
chromedriver_autoinstaller-0.6.3.dist-info/RECORD
